{
  "$schema": "https://json-schema.org/draft/2020-12/schema",
  "$id": "https://eureka.local/contracts/connectors/github_releases_connector_manifest.v0.json",
  "title": "Eureka GitHub Releases Connector Manifest v0",
  "type": "object",
  "additionalProperties": true,
  "x-status": "contract_only",
  "x-runtime_implemented": false,
  "x-live_enabled_by_default": false,
  "x-public_query_fanout_allowed": false,
  "x-downloads_allowed": false,
  "x-arbitrary_url_fetch_allowed": false,
  "x-repository_clone_allowed": false,
  "x-release_asset_download_allowed": false,
  "x-source_archive_download_allowed": false,
  "x-token_required_now": false,
  "x-source_cache_mutation_allowed_now": false,
  "x-evidence_ledger_mutation_allowed_now": false,
  "x-candidate_index_mutation_allowed_now": false,
  "x-master_index_mutation_allowed_now": false,
  "required": [
    "schema_version",
    "connector_id",
    "connector_kind",
    "status",
    "source_family",
    "supported_capabilities",
    "disabled_capabilities",
    "default_policy",
    "source_sync_worker_relationship",
    "source_cache_relationship",
    "evidence_ledger_relationship",
    "safety_defaults",
    "no_runtime_guarantees",
    "notes"
  ],
  "properties": {
    "schema_version": {
      "description": "Eureka GitHub Releases Connector Manifest v0 field: schema_version."
    },
    "connector_id": {
      "description": "Eureka GitHub Releases Connector Manifest v0 field: connector_id."
    },
    "connector_kind": {
      "description": "Eureka GitHub Releases Connector Manifest v0 field: connector_kind."
    },
    "status": {
      "description": "Eureka GitHub Releases Connector Manifest v0 field: status."
    },
    "source_family": {
      "description": "Eureka GitHub Releases Connector Manifest v0 field: source_family."
    },
    "supported_capabilities": {
      "description": "Eureka GitHub Releases Connector Manifest v0 field: supported_capabilities."
    },
    "disabled_capabilities": {
      "description": "Eureka GitHub Releases Connector Manifest v0 field: disabled_capabilities."
    },
    "default_policy": {
      "description": "Eureka GitHub Releases Connector Manifest v0 field: default_policy."
    },
    "source_sync_worker_relationship": {
      "description": "Eureka GitHub Releases Connector Manifest v0 field: source_sync_worker_relationship."
    },
    "source_cache_relationship": {
      "description": "Eureka GitHub Releases Connector Manifest v0 field: source_cache_relationship."
    },
    "evidence_ledger_relationship": {
      "description": "Eureka GitHub Releases Connector Manifest v0 field: evidence_ledger_relationship."
    },
    "safety_defaults": {
      "description": "Eureka GitHub Releases Connector Manifest v0 field: safety_defaults."
    },
    "no_runtime_guarantees": {
      "description": "Eureka GitHub Releases Connector Manifest v0 field: no_runtime_guarantees."
    },
    "notes": {
      "description": "Eureka GitHub Releases Connector Manifest v0 field: notes."
    }
  },
  "$defs": {
    "statuses": [
      "draft_example",
      "approval_required",
      "runtime_future",
      "disabled"
    ],
    "source_family": [
      "github_releases"
    ],
    "supported_capabilities": [
      "repository_release_metadata_future",
      "release_tag_metadata_future",
      "release_asset_metadata_summary_future",
      "latest_release_metadata_future",
      "release_date_version_summary_future",
      "release_prerelease_draft_status_summary_future"
    ],
    "disabled_capabilities": [
      "arbitrary_repository_fetch",
      "direct_public_query_fanout",
      "private_repository_access",
      "token_required_access",
      "repository_clone",
      "tag_fetch_runtime_now",
      "release_fetch_runtime_now",
      "release_asset_download",
      "source_archive_download",
      "raw_file_fetch",
      "blob_fetch",
      "tree_fetch",
      "org_or_user_bulk_crawl",
      "account_access",
      "upload",
      "install",
      "execute",
      "unbounded_crawl",
      "scraping",
      "bypass_access_restrictions",
      "raw_payload_dump",
      "malware_safety_decision",
      "rights_clearance_decision"
    ]
  }
}
